neospeech/__init__.py
neospeech/audio.py
neospeech/balance.py
neospeech/client.py
neospeech/errors.py
neospeech/models.py
neospeech/py.typed
neospeech/voices.py
neospeech_io-1.0.0.dist-info/licenses/LICENSE
neospeech_io-1.0.0.dist-info/METADATA
neospeech_io-1.0.0.dist-info/WHEEL
neospeech_io-1.0.0.dist-info/top_level.txt
neospeech_io-1.0.0.dist-info/RECORD
