Metadata-Version: 2.4
Name: neospeech-io
Version: 1.0.0
Summary: Official Python SDK for the NeoSpeech Text-to-Speech API
Home-page: https://github.com/neospeech/neospeech-python
Author: NeoSpeech
Author-email: NeoSpeech <support@neospeech.io>
License: MIT
Project-URL: Homepage, https://docs.neospeech.io
Project-URL: Documentation, https://docs.neospeech.io
Project-URL: Repository, https://github.com/neospeech/neospeech-python
Project-URL: Bug Reports, https://github.com/neospeech/neospeech-python/issues
Keywords: neospeech,text-to-speech,tts,speech-synthesis,voice,audio,ai,sdk
Classifier: Development Status :: 5 - Production/Stable
Classifier: Intended Audience :: Developers
Classifier: License :: OSI Approved :: MIT License
Classifier: Programming Language :: Python :: 3
Classifier: Programming Language :: Python :: 3.8
Classifier: Programming Language :: Python :: 3.9
Classifier: Programming Language :: Python :: 3.10
Classifier: Programming Language :: Python :: 3.11
Classifier: Programming Language :: Python :: 3.12
Classifier: Topic :: Software Development :: Libraries :: Python Modules
Classifier: Topic :: Multimedia :: Sound/Audio :: Speech
Requires-Python: >=3.8
License-File: LICENSE
Requires-Dist: requests>=2.25.0
Dynamic: author
Dynamic: home-page
Dynamic: license-file
Dynamic: requires-python
